ccodev3/__init__.py
ccodev3/codevclient.py
ccodev3-0.0.1.dist-info/LICENSE
ccodev3-0.0.1.dist-info/METADATA
ccodev3-0.0.1.dist-info/WHEEL
ccodev3-0.0.1.dist-info/top_level.txt
ccodev3-0.0.1.dist-info/RECORD
